{
  "schemaVersion": 1,
  "generatedAt": "2026-07-13T14:55:14.525Z",
  "sources": [
    {
      "id": "gdelt",
      "sourceType": "gdelt",
      "status": "failed",
      "count": 0
    },
    {
      "id": "hacker-news",
      "sourceType": "hacker-news",
      "status": "ok",
      "count": 16
    },
    {
      "id": "bbc-world",
      "sourceType": "rsshub",
      "status": "fallback",
      "count": 28,
      "transport": "native-rss"
    },
    {
      "id": "guardian-world",
      "sourceType": "rsshub",
      "status": "fallback",
      "count": 45,
      "transport": "native-rss"
    },
    {
      "id": "npr-news",
      "sourceType": "rsshub",
      "status": "fallback",
      "count": 10,
      "transport": "native-rss"
    },
    {
      "id": "al-jazeera",
      "sourceType": "rsshub",
      "status": "fallback",
      "count": 25,
      "transport": "native-rss"
    }
  ],
  "stories": [
    {
      "id": "cd7647004160c8dce4df",
      "title": "Trump claims he will reinstate Iranian blockade and US will charge fee for ships crossing strait of Hormuz – Middle East crisis live",
      "url": "https://www.theguardian.com/world/live/2026/jul/13/us-iran-strikes-middle-east-strait-of-hormuz-military-latest-news-updates",
      "source": "The Guardian",
      "sourceType": "rsshub",
      "sourceId": "guardian-world",
      "topic": "world",
      "publishedAt": "2026-07-13T14:38:46.000Z",
      "discoveredAt": "2026-07-13T14:55:14.525Z"
    },
    {
      "id": "6dd35027917a0262eeeb",
      "title": "Counter-terrorist police chief says ‘new evidence’ led to his team taking over investigation into Ann Widdecombe’s death – UK politics live",
      "url": "https://www.theguardian.com/politics/live/2026/jul/13/shabana-mahmood-migration-rochdale-grooming-gang-pakistan-visas-immigration-andy-burnham-labour",
      "source": "The Guardian",
      "sourceType": "rsshub",
      "sourceId": "guardian-world",
      "topic": "world",
      "publishedAt": "2026-07-13T14:37:42.000Z",
      "discoveredAt": "2026-07-13T14:55:14.525Z"
    },
    {
      "id": "447f40bb284ea5705969",
      "title": "Person reported killed during ICE operation in Maine, state house speaker says – US politics live",
      "url": "https://www.theguardian.com/us-news/live/2026/jul/13/congress-capitol-lindsey-graham-trump-republicans-democrats-us-politics-latest-news-updates",
      "source": "The Guardian",
      "sourceType": "rsshub",
      "sourceId": "guardian-world",
      "topic": "world",
      "publishedAt": "2026-07-13T14:37:25.000Z",
      "discoveredAt": "2026-07-13T14:55:14.525Z"
    },
    {
      "id": "af50b29a72a844846fa7",
      "title": "What is the EU’s plan to cut trade with illegal Israeli settlements?",
      "url": "https://www.aljazeera.com/news/2026/7/13/what-is-the-eus-plan-to-cut-trade-with-illegal-israeli-settlements?traffic_source=rss",
      "source": "Al Jazeera English",
      "sourceType": "rsshub",
      "sourceId": "al-jazeera",
      "topic": "world",
      "publishedAt": "2026-07-13T14:33:14.000Z",
      "discoveredAt": "2026-07-13T14:55:14.525Z"
    },
    {
      "id": "de3b50ca1c2a7796738f",
      "title": "JP Morgan boss pressed by US senator about bank’s contact with Jeffrey Epstein",
      "url": "https://www.theguardian.com/business/2026/jul/13/jp-morgan-boss-jamie-dimon-us-uk-jeffrey-epstein-elizabeth-warren",
      "source": "The Guardian",
      "sourceType": "rsshub",
      "sourceId": "guardian-world",
      "topic": "world",
      "publishedAt": "2026-07-13T14:26:38.000Z",
      "discoveredAt": "2026-07-13T14:55:14.525Z"
    },
    {
      "id": "c59c94cdda3266d27e51",
      "title": "Ukraine to present its anti-ballistic programme at Paris meeting today, Zelenskyy says – Europe live",
      "url": "https://www.theguardian.com/world/live/2026/jul/13/emmanuel-macron-keir-starmer-friedrich-merz-volodymyr-zelenskyy-coalition-of-the-willing-ukraine-russia-latest-news-updates",
      "source": "The Guardian",
      "sourceType": "rsshub",
      "sourceId": "guardian-world",
      "topic": "world",
      "publishedAt": "2026-07-13T14:25:35.000Z",
      "discoveredAt": "2026-07-13T14:55:14.525Z"
    },
    {
      "id": "3cdc55012d3d4161bc20",
      "title": "How Sheikh Hamad revolutionised Arab media through Al Jazeera",
      "url": "https://www.aljazeera.com/news/2026/7/13/how-sheikh-hamad-revolutionised-arab-media-through-al-jazeera?traffic_source=rss",
      "source": "Al Jazeera English",
      "sourceType": "rsshub",
      "sourceId": "al-jazeera",
      "topic": "world",
      "publishedAt": "2026-07-13T14:24:29.000Z",
      "discoveredAt": "2026-07-13T14:55:14.525Z"
    },
    {
      "id": "de13c521b4f416f98e75",
      "title": "Two teens arrested after five members of family killed in Illinois shooting",
      "url": "https://www.theguardian.com/us-news/2026/jul/13/east-st-louis-illinois-shooting-arrests",
      "source": "The Guardian",
      "sourceType": "rsshub",
      "sourceId": "guardian-world",
      "topic": "world",
      "publishedAt": "2026-07-13T14:19:01.000Z",
      "discoveredAt": "2026-07-13T14:55:14.525Z"
    },
    {
      "id": "bc231e1c19dd79870906",
      "title": "Yemeni government forces strike Sanaa airport",
      "url": "https://www.aljazeera.com/video/newsfeed/2026/7/13/yemeni-government-forces-strike-sanaa-airport?traffic_source=rss",
      "source": "Al Jazeera English",
      "sourceType": "rsshub",
      "sourceId": "al-jazeera",
      "topic": "world",
      "publishedAt": "2026-07-13T14:03:44.000Z",
      "discoveredAt": "2026-07-13T14:55:14.525Z"
    },
    {
      "id": "9fbe8936ed2a34eeeeb8",
      "title": "Show HN: Clawk – Give coding agents a disposable Linux VM, not your laptop",
      "url": "https://github.com/clawkwork/clawk",
      "source": "github.com",
      "sourceType": "hacker-news",
      "sourceId": "hacker-news",
      "topic": "technology",
      "publishedAt": "2026-07-13T14:02:03.000Z",
      "discoveredAt": "2026-07-13T14:55:14.525Z"
    },
    {
      "id": "6d7b045c237978ab8a9d",
      "title": "Killings continue on Del Monte farm in Kenya, families say, after G4S hired for security",
      "url": "https://www.theguardian.com/world/2026/jul/13/del-monte-pineapple-farm-kenya-deaths-g4s",
      "source": "The Guardian",
      "sourceType": "rsshub",
      "sourceId": "guardian-world",
      "topic": "world",
      "publishedAt": "2026-07-13T14:00:49.000Z",
      "discoveredAt": "2026-07-13T14:55:14.525Z"
    },
    {
      "id": "d3f15c01c946feb4c754",
      "title": "Britons to use e-gates in Switzerland as Starmer seals £5.2bn trade deal",
      "url": "https://www.theguardian.com/business/2026/jul/13/brits-e-gates-switzerland-keir-starmer-seals-trade-deal",
      "source": "The Guardian",
      "sourceType": "rsshub",
      "sourceId": "guardian-world",
      "topic": "world",
      "publishedAt": "2026-07-13T14:00:48.000Z",
      "discoveredAt": "2026-07-13T14:55:14.525Z"
    },
    {
      "id": "e4c5cc4295ad453dd952",
      "title": "Pilot fighting Colorado wildfire dies as plane crashes into reservoir",
      "url": "https://www.theguardian.com/us-news/2026/jul/13/colorado-pilot-dies-wildfire",
      "source": "The Guardian",
      "sourceType": "rsshub",
      "sourceId": "guardian-world",
      "topic": "world",
      "publishedAt": "2026-07-13T14:00:35.000Z",
      "discoveredAt": "2026-07-13T14:55:14.525Z"
    },
    {
      "id": "dd701737187a547610e8",
      "title": "EU sanctions nine people over alleged Russian cyber-spying campaign",
      "url": "https://www.aljazeera.com/news/2026/7/13/eu-sanctions-nine-people-over-alleged-russian-cyber-spying-campaign?traffic_source=rss",
      "source": "Al Jazeera English",
      "sourceType": "rsshub",
      "sourceId": "al-jazeera",
      "topic": "world",
      "publishedAt": "2026-07-13T13:59:54.000Z",
      "discoveredAt": "2026-07-13T14:55:14.525Z"
    },
    {
      "id": "92887e843ac4dbdc1efb",
      "title": "US and Iran exchange fresh wave of strikes as Tehran says diplomacy has proven ‘futile’",
      "url": "https://www.theguardian.com/world/2026/jul/13/us-iran-war-missile-strikes-news-attacks-strait-of-hormuz",
      "source": "The Guardian",
      "sourceType": "rsshub",
      "sourceId": "guardian-world",
      "topic": "world",
      "publishedAt": "2026-07-13T13:59:50.000Z",
      "discoveredAt": "2026-07-13T14:55:14.525Z"
    },
    {
      "id": "e5a41d6fc21c22ea420e",
      "title": "Hamas denies UN accusations over Gaza aid distribution interference",
      "url": "https://www.aljazeera.com/news/2026/7/13/hamas-denies-un-accusations-over-gaza-aid-distribution-interference?traffic_source=rss",
      "source": "Al Jazeera English",
      "sourceType": "rsshub",
      "sourceId": "al-jazeera",
      "topic": "world",
      "publishedAt": "2026-07-13T13:59:43.000Z",
      "discoveredAt": "2026-07-13T14:55:14.525Z"
    },
    {
      "id": "93bf54affbabd5d9fa23",
      "title": "VW chief confirms plan to cut 50,000 jobs as board rejects plant closures",
      "url": "https://www.theguardian.com/business/2026/jul/13/vw-cut-jobs-board-rejects-plant-closures-staff-restructuring",
      "source": "The Guardian",
      "sourceType": "rsshub",
      "sourceId": "guardian-world",
      "topic": "world",
      "publishedAt": "2026-07-13T13:42:21.000Z",
      "discoveredAt": "2026-07-13T14:55:14.525Z"
    },
    {
      "id": "5d8a401932a453d89f7f",
      "title": "Grok uploaded my user directory to xAI's servers",
      "url": "https://twitter.com/a_green_being/status/2076598897779020159",
      "source": "twitter.com",
      "sourceType": "hacker-news",
      "sourceId": "hacker-news",
      "topic": "technology",
      "publishedAt": "2026-07-13T13:39:59.000Z",
      "discoveredAt": "2026-07-13T14:55:14.525Z"
    },
    {
      "id": "e9842c2542b982c2af92",
      "title": "Burnham expected to vote in favour of Mahmood’s asylum system changes",
      "url": "https://www.theguardian.com/uk-news/2026/jul/13/andy-burnham-expected-to-vote-shabana-mahmood-asylum-system-changes",
      "source": "The Guardian",
      "sourceType": "rsshub",
      "sourceId": "guardian-world",
      "topic": "world",
      "publishedAt": "2026-07-13T13:38:32.000Z",
      "discoveredAt": "2026-07-13T14:55:14.525Z"
    },
    {
      "id": "a09065cccb7a9be70c76",
      "title": "Grok CLI uploaded the whole home directory to GCS",
      "url": "https://twitter.com/i/status/2076598897779020159",
      "source": "twitter.com",
      "sourceType": "hacker-news",
      "sourceId": "hacker-news",
      "topic": "technology",
      "publishedAt": "2026-07-13T13:35:32.000Z",
      "discoveredAt": "2026-07-13T14:55:14.525Z"
    },
    {
      "id": "f24a78f4b8ae9a701037",
      "title": "FIFA World Cup England vs Argentina: What to know ahead of second semifinal",
      "url": "https://www.aljazeera.com/sports/2026/7/13/argentina-england-fifa-world-cup-semifinal-prediction-messi-kane-venue?traffic_source=rss",
      "source": "Al Jazeera English",
      "sourceType": "rsshub",
      "sourceId": "al-jazeera",
      "topic": "world",
      "publishedAt": "2026-07-13T13:21:48.000Z",
      "discoveredAt": "2026-07-13T14:55:14.525Z"
    },
    {
      "id": "8d40b6060ed6dc83ad12",
      "title": "What is Japan’s new intelligence agency, and why is Tokyo building it?",
      "url": "https://www.aljazeera.com/news/2026/7/13/what-is-japans-new-intelligence-agency-and-why-is-tokyo-building-it?traffic_source=rss",
      "source": "Al Jazeera English",
      "sourceType": "rsshub",
      "sourceId": "al-jazeera",
      "topic": "world",
      "publishedAt": "2026-07-13T13:07:15.000Z",
      "discoveredAt": "2026-07-13T14:55:14.525Z"
    },
    {
      "id": "0fa4cb1a5882979b1cb2",
      "title": "EU chief pledges social media ban to protect children from ‘predatory algorithms’",
      "url": "https://www.theguardian.com/world/2026/jul/13/eu-social-media-ban-children-under-13-ursula-von-der-leyen",
      "source": "The Guardian",
      "sourceType": "rsshub",
      "sourceId": "guardian-world",
      "topic": "world",
      "publishedAt": "2026-07-13T12:52:36.000Z",
      "discoveredAt": "2026-07-13T14:55:14.525Z"
    },
    {
      "id": "28d2a6af7f2de1956de1",
      "title": "What will happen to Trump’s agenda after Lindsey Graham’s death?",
      "url": "https://www.aljazeera.com/news/2026/7/13/what-will-happen-to-trumps-agenda-after-lindsey-grahams-death?traffic_source=rss",
      "source": "Al Jazeera English",
      "sourceType": "rsshub",
      "sourceId": "al-jazeera",
      "topic": "world",
      "publishedAt": "2026-07-13T12:41:22.000Z",
      "discoveredAt": "2026-07-13T14:55:14.525Z"
    },
    {
      "id": "7c712e1e1e54cf7ef32c",
      "title": "The late Sheikh Hamad bin Khalifa Al Thani’s legacy on women’s reform",
      "url": "https://www.aljazeera.com/video/newsfeed/2026/7/13/the-late-sheikh-hamad-bin-khalifa-al-thanis-legacy-on-womens-reform?traffic_source=rss",
      "source": "Al Jazeera English",
      "sourceType": "rsshub",
      "sourceId": "al-jazeera",
      "topic": "world",
      "publishedAt": "2026-07-13T12:36:41.000Z",
      "discoveredAt": "2026-07-13T14:55:14.525Z"
    },
    {
      "id": "71ac788ed5a8b5278c2b",
      "title": "Irish police to engage with Jordanian force in murder investigation",
      "url": "https://www.bbc.co.uk/news/articles/c621p1zne6qo?at_medium=RSS&at_campaign=rss",
      "source": "BBC News",
      "sourceType": "rsshub",
      "sourceId": "bbc-world",
      "topic": "world",
      "publishedAt": "2026-07-13T12:32:45.000Z",
      "discoveredAt": "2026-07-13T14:55:14.525Z"
    },
    {
      "id": "9c874374e648d593606f",
      "title": "At least 28 killed, 25 critically injured after fire engulfs Bangkok bar",
      "url": "https://www.bbc.co.uk/news/articles/c24yev53q06o?at_medium=RSS&at_campaign=rss",
      "source": "BBC News",
      "sourceType": "rsshub",
      "sourceId": "bbc-world",
      "topic": "world",
      "publishedAt": "2026-07-13T12:32:08.000Z",
      "discoveredAt": "2026-07-13T14:55:14.525Z"
    },
    {
      "id": "01220b60b8655278e9df",
      "title": "Street in Illinois named after murdered Palestinian boy",
      "url": "https://www.aljazeera.com/video/newsfeed/2026/7/13/street-in-illinois-named-after-murdered-palestinian-boy?traffic_source=rss",
      "source": "Al Jazeera English",
      "sourceType": "rsshub",
      "sourceId": "al-jazeera",
      "topic": "world",
      "publishedAt": "2026-07-13T12:31:36.000Z",
      "discoveredAt": "2026-07-13T14:55:14.525Z"
    },
    {
      "id": "7dc1acb2cea7a53c5764",
      "title": "Firefighting planes scrambled from south of France to tackle huge wildfire near Paris",
      "url": "https://www.theguardian.com/world/2026/jul/13/france-fires-wildfires-fointaineblue-forest-paris",
      "source": "The Guardian",
      "sourceType": "rsshub",
      "sourceId": "guardian-world",
      "topic": "world",
      "publishedAt": "2026-07-13T12:30:18.000Z",
      "discoveredAt": "2026-07-13T14:55:14.525Z"
    },
    {
      "id": "7869d5882ee8944f0c0e",
      "title": "Keystone pipeline operator agrees to pay $26.9m penalty over Kansas oil spill",
      "url": "https://www.theguardian.com/us-news/2026/jul/13/keystone-pipeline-operator-settlement-kansas-oil-spill",
      "source": "The Guardian",
      "sourceType": "rsshub",
      "sourceId": "guardian-world",
      "topic": "world",
      "publishedAt": "2026-07-13T12:16:01.000Z",
      "discoveredAt": "2026-07-13T14:55:14.525Z"
    },
    {
      "id": "9f46c025b4c80e090cd8",
      "title": "March to July: What’s different as US-Iran fighting escalates again?",
      "url": "https://www.aljazeera.com/news/2026/7/13/march-to-july-whats-different-as-us-iran-fighting-escalates-again?traffic_source=rss",
      "source": "Al Jazeera English",
      "sourceType": "rsshub",
      "sourceId": "al-jazeera",
      "topic": "world",
      "publishedAt": "2026-07-13T12:12:46.000Z",
      "discoveredAt": "2026-07-13T14:55:14.525Z"
    },
    {
      "id": "563cb1553114a8f9b277",
      "title": "A versatile actor whose roles went far beyond Jurassic Park - Sam Neill dies aged 78",
      "url": "https://www.bbc.co.uk/news/articles/cx2wrvqq9rlo?at_medium=RSS&at_campaign=rss",
      "source": "BBC News",
      "sourceType": "rsshub",
      "sourceId": "bbc-world",
      "topic": "world",
      "publishedAt": "2026-07-13T12:10:38.000Z",
      "discoveredAt": "2026-07-13T14:55:14.525Z"
    },
    {
      "id": "65d822ca02be39e48865",
      "title": "At least 27 killed in fire at Bangkok pub with another 22 critically injured",
      "url": "https://www.theguardian.com/world/2026/jul/12/at-least-27-killed-in-blaze-at-bangkok-pub-thai-officials-say",
      "source": "The Guardian",
      "sourceType": "rsshub",
      "sourceId": "guardian-world",
      "topic": "world",
      "publishedAt": "2026-07-13T12:05:28.000Z",
      "discoveredAt": "2026-07-13T14:55:14.525Z"
    },
    {
      "id": "ac12d2849108b51f669c",
      "title": "The U.S.-Iran ceasefire grows more distant. And, Congress faces a consequential week",
      "url": "https://www.npr.org/2026/07/13/g-s1-133269/up-first-newsletter-us-iran-war-congress-lindsey-graham-gaza-israel-hussam-abu-safiya",
      "source": "NPR News",
      "sourceType": "rsshub",
      "sourceId": "npr-news",
      "topic": "world",
      "publishedAt": "2026-07-13T12:02:33.000Z",
      "discoveredAt": "2026-07-13T14:55:14.525Z"
    },
    {
      "id": "53e9bbe14b0b93501abd",
      "title": "Trump officials accused of stacking top chemical safety board with industry ‘mouthpieces’",
      "url": "https://www.theguardian.com/us-news/2026/jul/13/trump-chemical-safety-board",
      "source": "The Guardian",
      "sourceType": "rsshub",
      "sourceId": "guardian-world",
      "topic": "world",
      "publishedAt": "2026-07-13T12:00:47.000Z",
      "discoveredAt": "2026-07-13T14:55:14.525Z"
    },
    {
      "id": "19bb42ae656d6bcbccdb",
      "title": "Young men report more ‘sextortion’ than any other age group, Australia’s online safety watchdog says",
      "url": "https://www.theguardian.com/technology/2026/jul/13/young-men-report-more-sextortion-than-any-other-age-group-australias-online-safety-watchdog-says-ntwnfb",
      "source": "The Guardian",
      "sourceType": "rsshub",
      "sourceId": "guardian-world",
      "topic": "world",
      "publishedAt": "2026-07-13T12:00:46.000Z",
      "discoveredAt": "2026-07-13T14:55:14.525Z"
    },
    {
      "id": "174999abdc723263b322",
      "title": "'Hero, legend, sweetheart': Tributes to Jurassic Park actor Sam Neill, who has died aged 78",
      "url": "https://www.bbc.co.uk/news/articles/cy06e5e1lygo?at_medium=RSS&at_campaign=rss",
      "source": "BBC News",
      "sourceType": "rsshub",
      "sourceId": "bbc-world",
      "topic": "world",
      "publishedAt": "2026-07-13T11:52:55.000Z",
      "discoveredAt": "2026-07-13T14:55:14.525Z"
    },
    {
      "id": "d1b99f33d37bbcfada07",
      "title": "Show HN: DOM-docx – HTML to native, editable Word docs (MIT)",
      "url": "https://github.com/floodtide/dom-docx",
      "source": "github.com",
      "sourceType": "hacker-news",
      "sourceId": "hacker-news",
      "topic": "technology",
      "publishedAt": "2026-07-13T11:51:56.000Z",
      "discoveredAt": "2026-07-13T14:55:14.525Z"
    },
    {
      "id": "b3a7f79a58f45802b6b0",
      "title": "South Korea rolls out plan to tackle youth suicide crisis",
      "url": "https://www.aljazeera.com/video/newsfeed/2026/7/13/south-korea-rolls-out-plan-to-tackle-youth-suicide-crisis?traffic_source=rss",
      "source": "Al Jazeera English",
      "sourceType": "rsshub",
      "sourceId": "al-jazeera",
      "topic": "world",
      "publishedAt": "2026-07-13T11:48:52.000Z",
      "discoveredAt": "2026-07-13T14:55:14.525Z"
    },
    {
      "id": "c92a7c0b7d1a35dd7e44",
      "title": "Ann Widdecombe death: counter-terrorism police take over investigation",
      "url": "https://www.theguardian.com/uk-news/2026/jul/13/ann-widdecombe-counter-terrorism-police-investigation",
      "source": "The Guardian",
      "sourceType": "rsshub",
      "sourceId": "guardian-world",
      "topic": "world",
      "publishedAt": "2026-07-13T11:46:01.000Z",
      "discoveredAt": "2026-07-13T14:55:14.525Z"
    },
    {
      "id": "42c2742a9ea6e6261dee",
      "title": "Control the Ideas, Not the Code",
      "url": "https://antirez.com/news/169",
      "source": "antirez.com",
      "sourceType": "hacker-news",
      "sourceId": "hacker-news",
      "topic": "technology",
      "publishedAt": "2026-07-13T11:45:36.000Z",
      "discoveredAt": "2026-07-13T14:55:14.525Z"
    },
    {
      "id": "16b77a70ccaa19a612f2",
      "title": "The SpaceX IPO made history. One month on has it lost momentum?",
      "url": "https://www.bbc.co.uk/news/articles/c3wyj6e4210o?at_medium=RSS&at_campaign=rss",
      "source": "BBC News",
      "sourceType": "rsshub",
      "sourceId": "bbc-world",
      "topic": "world",
      "publishedAt": "2026-07-13T11:45:25.000Z",
      "discoveredAt": "2026-07-13T14:55:14.525Z"
    },
    {
      "id": "bff3c11b971029235977",
      "title": "UK to list Iran’s Islamic Revolutionary Guard Corps as terrorist organisation",
      "url": "https://www.theguardian.com/politics/2026/jul/13/uk-list-iran-islamic-revolutionary-guard-corps-irgc-terrorist-organisation",
      "source": "The Guardian",
      "sourceType": "rsshub",
      "sourceId": "guardian-world",
      "topic": "world",
      "publishedAt": "2026-07-13T11:42:28.000Z",
      "discoveredAt": "2026-07-13T14:55:14.525Z"
    },
    {
      "id": "f721bda5d421c076ae52",
      "title": "Al Jazeera bids farewell to founder Sheikh Hamad",
      "url": "https://www.aljazeera.com/video/newsfeed/2026/7/13/al-jazeera-bids-farewell-to-founder-sheikh-hamad?traffic_source=rss",
      "source": "Al Jazeera English",
      "sourceType": "rsshub",
      "sourceId": "al-jazeera",
      "topic": "world",
      "publishedAt": "2026-07-13T11:38:09.000Z",
      "discoveredAt": "2026-07-13T14:55:14.525Z"
    },
    {
      "id": "55b7a42cfecfbbb8a831",
      "title": "Yemen government says its forces attacked Sanaa airport",
      "url": "https://www.aljazeera.com/news/2026/7/13/yemen-govt-says-its-forces-attacked-sanaa-airport?traffic_source=rss",
      "source": "Al Jazeera English",
      "sourceType": "rsshub",
      "sourceId": "al-jazeera",
      "topic": "world",
      "publishedAt": "2026-07-13T11:38:03.000Z",
      "discoveredAt": "2026-07-13T14:55:14.525Z"
    },
    {
      "id": "7f5b961ffd2ebe0c4c27",
      "title": "German court convicts Iraqi couple of enslaving Yazidi girls",
      "url": "https://www.bbc.co.uk/news/articles/cg53rp4e2j4o?at_medium=RSS&at_campaign=rss",
      "source": "BBC News",
      "sourceType": "rsshub",
      "sourceId": "bbc-world",
      "topic": "world",
      "publishedAt": "2026-07-13T11:36:18.000Z",
      "discoveredAt": "2026-07-13T14:55:14.525Z"
    },
    {
      "id": "e754d84b4b022cb7f56e",
      "title": "Will the 2030 World Cup expand to 64 teams? What FIFA’s Infantino says",
      "url": "https://www.aljazeera.com/news/2026/7/13/gianni-infantino-64-teams-expansion-comments-fifa-2030-world-cup?traffic_source=rss",
      "source": "Al Jazeera English",
      "sourceType": "rsshub",
      "sourceId": "al-jazeera",
      "topic": "world",
      "publishedAt": "2026-07-13T11:29:20.000Z",
      "discoveredAt": "2026-07-13T14:55:14.525Z"
    },
    {
      "id": "cbc1ec2766f9311adbf4",
      "title": "Plan to restore nature in England by 2030 criticised as ‘completely insufficient’",
      "url": "https://www.theguardian.com/environment/2026/jul/13/england-rewilding-plan-restore-nature-2030-criticised",
      "source": "The Guardian",
      "sourceType": "rsshub",
      "sourceId": "guardian-world",
      "topic": "world",
      "publishedAt": "2026-07-13T11:27:48.000Z",
      "discoveredAt": "2026-07-13T14:55:14.525Z"
    }
  ]
}
